[
  {
    "value": "AndhraPradesh",
    "label": "Andhra Pradesh"
  },
  {
    "value": "ArunachalPradesh",
    "label": "Arunachal Pradesh"
  },
  {
    "value": "Assam",
    "label": "Assam"
  },
  {
    "value": "Bihar",
    "label": "Bihar"
  },
  {
    "value": "Chhattisgarh",
    "label": "Chhattisgarh"
  },
  {
    "value": "Goa",
    "label": "Goa"
  },
  {
    "value": "Gujarat",
    "label": "Gujarat"
  },
  {
    "value": "Haryana",
    "label": "Haryana"
  },
  {
    "value": "HimachalPradesh",
    "label": "Himachal Pradesh"
  },
  {
    "value": "JammuAndKashmir",
    "label": "Jammu and Kashmir"
  },
  {
    "value": "Jharkhand",
    "label": "Jharkhand"
  },
  {
    "value": "Karnataka",
    "label": "Karnataka"
  },
  {
    "value": "Kerala",
    "label": "Kerala"
  },
  {
    "value": "MadhyaPradesh",
    "label": "Madhya Pradesh"
  },
  {
    "value": "Maharashtra",
    "label": "Maharashtra"
  },
  {
    "value": "Manipur",
    "label": "Manipur"
  },
  {
    "value": "Meghalaya",
    "label": "Meghalaya"
  },
  {
    "value": "Mizoram",
    "label": "Mizoram"
  },
  {
    "value": "Nagaland",
    "label": "Nagaland"
  },
  {
    "value": "Odisha",
    "label": "Odisha"
  },
  {
    "value": "Punjab",
    "label": "Punjab"
  },
  {
    "value": "Rajasthan",
    "label": "Rajasthan"
  },
  {
    "value": "Sikkim",
    "label": "Sikkim"
  },
  {
    "value": "TamilNadu",
    "label": "Tamil Nadu"
  },
  {
    "value": "Telangana",
    "label": "Telangana"
  },
  {
    "value": "Tripura",
    "label": "Tripura"
  },
  {
    "value": "Uttarakhand",
    "label": "Uttarakhand"
  },
  {
    "value": "UttarPradesh",
    "label": "Uttar Pradesh"
  },
  {
    "value": "WestBengal",
    "label": "West Bengal"
  },
  {
    "value": "AndamanAndNicobarIslands",
    "label": "Andaman and Nicobar Islands"
  },
  {
    "value": "Chandigarh",
    "label": "Chandigarh"
  },
  {
    "value": "DadraAndNagarHaveli",
    "label": "Dadra and Nagar Haveli"
  },
  {
    "value": "DamanAndDiu",
    "label": "Daman and Diu"
  },
  {
    "value": "Delhi",
    "label": "Delhi"
  },
  {
    "value": "Lakshadweep",
    "label": "Lakshadweep"
  }
]
